cryex/__init__.py
cryex/core.py
cryex/kraken.py
cryex/model.py
cryex/poloniex.py
cryex/coins/__init__.py
cryex/coins/poloniex.py
cryex-0.1.21.dist-info/top_level.txt
cryex-0.1.21.dist-info/METADATA
cryex-0.1.21.dist-info/DESCRIPTION.rst
cryex-0.1.21.dist-info/metadata.json
cryex-0.1.21.dist-info/WHEEL
cryex-0.1.21.dist-info/RECORD
