Metadata-Version: 2.0
Name: cryex
Version: 0.1.21
Summary: Clients for Ethereum cryptocurrency exchanges
Home-page: https://github.com/walkr/cryex
Author: Tony Walker
Author-email: walkr.walkr@gmail.com
License: MIT
Keywords: cryex
Platform: UNKNOWN
Classifier: Development Status :: 2 - Pre-Alpha
Classifier: Intended Audience :: Developers
Classifier: License :: OSI Approved :: MIT License
Classifier: Natural Language :: English
Classifier: Programming Language :: Python :: 2.7
Classifier: Programming Language :: Python :: 3
Classifier: Programming Language :: Python :: 3.3
Classifier: Programming Language :: Python :: 3.4
Classifier: Programming Language :: Python :: 3.5
Requires-Dist: requests
